calculator_mlotfic/__init__.py
calculator_mlotfic/calculator.py
calculator_mlotfic-0.0.1.dist-info/LICENSE
calculator_mlotfic-0.0.1.dist-info/METADATA
calculator_mlotfic-0.0.1.dist-info/WHEEL
calculator_mlotfic-0.0.1.dist-info/top_level.txt
calculator_mlotfic-0.0.1.dist-info/RECORD
