Metadata-Version: 2.1
Name: calculator-mlotfic
Version: 0.0.1
Summary: This is a simple class libray for calculator
Author-email: Mahmoud Lotfi <aem@6236.com>
License: MIT License        
Project-URL: Homepage, https://github.com/mlotfic/calculator
Project-URL: Bug Tracker, https://github.com/mlotfic/calculator/issues
Classifier: Programming Language :: Python :: 3
Classifier: License :: OSI Approved :: MIT License
Classifier: Operating System :: OS Independent
Requires-Python: >=3.6
License-File: LICENSE
